texvars/__init__.py
texvars/main.py
texvars-0.2.0.dist-info/licenses/LICENSE.txt
texvars-0.2.0.dist-info/METADATA
texvars-0.2.0.dist-info/WHEEL
texvars-0.2.0.dist-info/top_level.txt
texvars-0.2.0.dist-info/RECORD
